osx_trash.py
setup.py
osx_trash.egg-info/PKG-INFO
osx_trash.egg-info/SOURCES.txt
osx_trash.egg-info/dependency_links.txt
osx_trash.egg-info/entry_points.txt
osx_trash.egg-info/not-zip-safe
osx_trash.egg-info/top_level.txt