Metadata-Version: 1.0
Name: osx-trash
Version: 1.0.0
Summary: An extendible utility for moving files to the trash, from the commandline, on OS X.
Home-page: https://github.com/moogar0880/osx_trash
Author: Jonathan Nappi
Author-email: moogar@comcast.net
License: http://www.gnu.org/copyleft/gpl.html
Platform: OS X
